cosmic_reach/__init__.py
cosmic_reach/client/__init__.py
cosmic_reach/client/base.py
cosmic_reach/client/client.py
cosmic_reach/common/__init__.py
cosmic_reach/common/events.py
cosmic_reach/common/types.py
cosmic_reach/crbin/__init__.py
cosmic_reach/io/__init__.py
cosmic_reach/io/htypes.py
cosmic_reach/io/serializer.py
cosmic_reach/io/types.py
cosmic_reach/io/wjson.py
cosmic_reach/protocol/__init__.py
cosmic_reach/protocol/enums/__init__.py
cosmic_reach/protocol/generic.py
cosmic_reach/protocol/packets/__init__.py
cosmic_reach/protocol/packets/blockentities.py
cosmic_reach/protocol/packets/blocks.py
cosmic_reach/protocol/packets/entities.py
cosmic_reach/protocol/packets/general.py
cosmic_reach/protocol/packets/items.py
cosmic_reach/protocol/packets/meta.py
cosmic_reach/protocol/packets/sounds.py
cosmic_reach/server/__init__.py
cosmic_reach/server/base.py
cosmic_reach/server/general.py
cosmic_reach/server/server.py
cosmic_reach/types/__init__.py
cosmic_reach/types/bin/__init__.py
cosmic_reach/types/bin/entities.py
cosmic_reach/types/bin/java.py
cosmic_reach/types/json/__init__.py
cosmic_reach/types/json/accounts.py
cosmic_reach/types/json/entities.py
cosmic_reach/types/json/java.py
cosmic_reach/versions/__init__.py
cosmic_reach/versions/enums.py
cosmic_reach/versions/types.py
cosmic_reach-0.1.2.dist-info/LICENSE
cosmic_reach-0.1.2.dist-info/METADATA
cosmic_reach-0.1.2.dist-info/WHEEL
cosmic_reach-0.1.2.dist-info/RECORD
