Metadata-Version: 2.3
Name: cosmic-reach
Version: 0.1.2
Summary: THIS PROJECT IS NOT AFFILIATED WITH OR SUPPORTED BY COSMIC REACH / FINALFOREACH! This is a python implementaion of Cosmic Reach's protocol.
License: GPL-3.0
Author: JoJoJux
Author-email: info@jojojux.de
Requires-Python: >=3.13,<4.0
Classifier: License :: OSI Approved :: GNU General Public License v3 (GPLv3)
Classifier: Programming Language :: Python :: 3
Classifier: Programming Language :: Python :: 3.13
Requires-Dist: dataclasses-json (>=0.6.7,<0.7.0)
Requires-Dist: dotenv (>=0.9.9,<0.10.0)
Requires-Dist: requests (>=2.32.3,<3.0.0)
